appdirs-stubs/METADATA.toml
appdirs-stubs/__init__.pyi
types_appdirs-1.4.3.4.dist-info/METADATA
types_appdirs-1.4.3.4.dist-info/WHEEL
types_appdirs-1.4.3.4.dist-info/top_level.txt
types_appdirs-1.4.3.4.dist-info/RECORD
